{"name":"t:sections.header.name","type":"header","sections":{"announcement-bar":{"type":"announcement-bar","blocks":{"acbf15ac-e532-49ff-821f-9e88fd723533":{"type":"announcement","disabled":true,"settings":{"text":"FREE SHIPPING ON ALL ORDERS!","link":""}},"bacd9e0c-3210-4994-86be-4b6aaad6dfe3":{"type":"announcement","disabled":true,"settings":{"text":"SITE WIDE BLOWOUT SALE!","link":""}},"b07dd984-dd2d-4426-ad41-c847208af697":{"type":"announcement","disabled":true,"settings":{"text":"OTJ X MVP collab available now at - www.otjmonopoly.com","link":""}}},"block_order":["acbf15ac-e532-49ff-821f-9e88fd723533","bacd9e0c-3210-4994-86be-4b6aaad6dfe3","b07dd984-dd2d-4426-ad41-c847208af697"],"settings":{}},"header":{"type":"header","settings":{"logo_position":"top-center","menu":"main-menu","show_line_separator":false,"color_scheme":"inverse"}}},"order":["announcement-bar","header"]}